pndex.py
pndex-0.1.6.dist-info/LICENSE
pndex-0.1.6.dist-info/METADATA
pndex-0.1.6.dist-info/WHEEL
pndex-0.1.6.dist-info/top_level.txt
pndex-0.1.6.dist-info/RECORD
