Metadata-Version: 2.1
Name: pndex
Version: 0.1.6
Summary: A Python package to manage all python files in a folder at once in console
Home-page: https://github.com/adityadand/pndex
Author: Aditya Dand
Author-email: dandaditya@gmail.com
License: MIT
Platform: UNKNOWN
Classifier: License :: OSI Approved :: MIT License
Classifier: Programming Language :: Python :: 3
Classifier: Programming Language :: Python :: 3.8
Requires-Dist: pyfiglet
Requires-Dist: importlib
Requires-Dist: pylint
